naviai_voiceprint/__init__.py
naviai_voiceprint/client.py
naviai_voiceprint/config.py
naviai_voiceprint/error_mapper.py
naviai_voiceprint/error_types.py
naviai_voiceprint/errors.py
naviai_voiceprint/utils.py
naviai_voiceprint/engines/__init__.py
naviai_voiceprint/engines/base.py
naviai_voiceprint/engines/tencent.py
naviai_voiceprint/engines/xunfei.py
naviai_voiceprint-0.2.0.dist-info/METADATA
naviai_voiceprint-0.2.0.dist-info/WHEEL
naviai_voiceprint-0.2.0.dist-info/top_level.txt
naviai_voiceprint-0.2.0.dist-info/RECORD
