Metadata-Version: 2.4
Name: naviai-voiceprint
Version: 0.2.0
Summary: Unified voiceprint recognition SDK (Xunfei / Tencent)
Author-email: Leslie_lin <2090616614@qq.com>
License: MIT
Project-URL: Homepage, https://github.com/yourname/naviai_voiceprint
Requires-Python: >=3.8
Requires-Dist: requests>=2.28.0
Provides-Extra: tencent
Requires-Dist: tencentcloud-sdk-python>=3.0.0; extra == "tencent"
Provides-Extra: dev
Requires-Dist: pytest>=7.0.0; extra == "dev"
